{
    "PlayerData":{
        "position":"startingRoom",
        "":""
    },
    "Start":{
        "startingRoom" : {
            "north": "vase",
            "south":"",
            "west":"",
            "east":"",
            "properties":{},
            "data":{
                "kills":0,
                "passable":1
            }
        },
        "vase" : {
            "north": "splitPath1",
            "south":"startingRoom",
            "west":"",
            "east":"secretRoom",
            "properties":{},
            "data":{
                "kills":0,
                "passable":1,
                "item":"vase"
            }
        },
        "splitPath1" : {
            "north": "",
            "south":"vase",
            "west":"splitPath2",
            "east":"rickyBridge",
            "properties":{},
            "data":{
                "kills":0,
                "passable":1
            }            
        },
        "splitPath2":{
            "north": "cornerToStairs",
            "south":"vasePlace",
            "west":"",
            "east":"splitPath1",
            "properties":{},
            "data":{
                "kills":0,
                "passable":1
            }
        },
        "vasePlace":{
            "north": "splitPath2",
            "south":"cornerToDark",
            "west":"",
            "east":"",
            "properties":{},
            "data":{
                "kills":0,
                "passable":1,
                "secretItem":"vase"
            }
        },
        "cornerToDark":{
            "north": "vasePlace",
            "south":"",
            "west":"darkCorridor",
            "east":"",
            "properties":{},
            "data":{
                "kills":0,
                "passable":1
            }
        },
        "darkCorridor":{
            "north": "",
            "south":"",
            "west":"saveRoom1",
            "east":"cornerToDark",
            "properties":{},
            "data":{
                "kills":0,
                "passable":1
            }
        },    
        "saveRoom1":{
            "north": "",
            "south":"",
            "west":"",
            "east":"darkCorridor",
            "properties":{},
            "data":{
                "kills":0,
                "passable":1
            }
        },
        "secretRoom":{
            "north": "",
            "south":"Vase",
            "west":"rickyBridge",
            "east":"",
            "properties":{},
            "data":{
                "kills":0,
                "passable":1
            }
        },
        "rickyBridge":{
            "north": "",
            "south":"",
            "west":"splitPath1",
            "east":"",
            "properties":{
                "lock-msg":"locked"
            },
            "data":{
                "kills":1,
                "passable":0
            }
        },
        "cornerToStairs":{
            "north": "",
            "south":"splitPath2",
            "west":"stairs",
            "east":"",
            "properties":{},
            "data":{
                "kills":0,
                "passable":1
            }
        },
        "stairs":{
            "north": "",
            "south":"",
            "west":"splitPathSecret",
            "east":"cornerToStairs",
            "properties":{},
            "data":{
                "kills":0,
                "passable":1
            }
        },
        "splitPathSecret":{
            "north": "stairs",
            "south":"secretItem",
            "west":"",
            "east":"stairs2",
            "properties":{},
            "data":{
                "kills":0,
                "passable":1
            }
        },
        "stairs2":{
            "north": "startingRoom",
            "south":"splitPathSecret",
            "west":"",
            "east":"",
            "properties":{},
            "data":{
                "kills":0,
                "passable":1
            }
        },
        "secretItem":{
            "north": "splitPathSecret",
            "south":"",
            "west":"",
            "east":"",
            "properties":{
                "lock-msg":"locked"
            },
            "data":{
                "kills":0,
                "passable":0,
                "secretItem":"Fancy China Teapot"
            }
        }


    }
}